wa_leg_api/__init__.py
wa_leg_api/amendment.py
wa_leg_api/committee.py
wa_leg_api/committeeaction.py
wa_leg_api/committeemeeting.py
wa_leg_api/exceptions.py
wa_leg_api/legislation.py
wa_leg_api/legislativedocument.py
wa_leg_api/make_stubs.py
wa_leg_api/rcwciteaffected.py
wa_leg_api/sessionlaw.py
wa_leg_api/sponsor.py
wa_leg_api/waleg.py
wa_leg_api-0.4.0.dist-info/LICENSE
wa_leg_api-0.4.0.dist-info/METADATA
wa_leg_api-0.4.0.dist-info/WHEEL
wa_leg_api-0.4.0.dist-info/top_level.txt
wa_leg_api-0.4.0.dist-info/RECORD
