Metadata-Version: 2.1
Name: wa-leg-api
Version: 0.4.0
Summary: A python API for the Washington State Legislature web services
Author: Janet Carson
License: MIT License
Project-URL: repository, https://github.com/j-carson/wa-leg-api
Project-URL: documentation, https://wa-leg-api.readthedocs.io
Keywords: government-data,washington,washington-state,legislature
Classifier: Development Status :: 3 - Alpha
Classifier: Intended Audience :: Developers
Classifier: License :: OSI Approved :: MIT License
Classifier: Programming Language :: Python :: 3.8
Classifier: Programming Language :: Python :: 3.9
Classifier: Programming Language :: Python :: 3.10
Classifier: Programming Language :: Python :: 3.11
Classifier: Operating System :: OS Independent
License-File: LICENSE
Requires-Dist: beautifulsoup4
Requires-Dist: requests
Requires-Dist: python-dateutil
Requires-Dist: lxml
Provides-Extra: dev
Requires-Dist: nox ; extra == 'dev'
Requires-Dist: pytest ; extra == 'dev'
Requires-Dist: pre-commit ; extra == 'dev'
Provides-Extra: docs
Requires-Dist: sphinx ; extra == 'docs'
Requires-Dist: myst-parser ; extra == 'docs'
Requires-Dist: pydata-sphinx-theme ; extra == 'docs'
Provides-Extra: upload
Requires-Dist: twine ; extra == 'upload'
Requires-Dist: build ; extra == 'upload'
Requires-Dist: setuptools ; extra == 'upload'
Requires-Dist: wheel ; extra == 'upload'
